Metadata-Version: 1.1
Name: memento-test
Version: 0.1.3
Summary: A Memento Test Suite
Home-page: https://github.com/mementoweb/memento_test
Author: Harihar Shankar
Author-email: hariharshankar@gmail.com
License: UNKNOWN
Keywords: memento http test
Platform: UNKNOWN
Classifier: Intended Audience :: Developers
Classifier: License :: OSI Approved :: BSD License
Classifier: Operating System :: OS Independent
Classifier: Topic :: Internet :: WWW/HTTP
Classifier: Topic :: Scientific/Engineering
Classifier: Topic :: Software Development :: Libraries :: Python Modules
Classifier: Topic :: Utilities
Classifier: Programming Language :: Python :: 2.7
Classifier: Programming Language :: Python :: 3.4
